<?xml version="1.0"?>
<Requests><Request><WebSalesOrder><SalesOrderNumber>#GBP109685</SalesOrderNumber><SalesOrderReference>5029755715662</SalesOrderReference><SalesOrderDate>2023-11-22T10:33:36+00:00</SalesOrderDate><CurrencyCode>GBP</CurrencyCode><CourierName>Royal Mail</CourierName><CourierService>RMTRACKEDSTDNOSIG</CourierService><Notes>Package_Type_3</Notes><GroupReference>Package_Type_3</GroupReference><OrderType>Web</OrderType></WebSalesOrder><DeliveryDetails><City>Derby</City><CountryCode>GB</CountryCode><EmailAddress>patriciamchurch@aol.com</EmailAddress><FirstName>Patricia</FirstName><LastName>Church</LastName><Line1>31 Silverburn Drive</Line1><Line2>Oakwood</Line2><PhoneNumber>+44 1332833961</PhoneNumber><PostcodeZip>DE21 2JJ</PostcodeZip></DeliveryDetails><SalesOrderHeader><DCCode>DCCL01</DCCode></SalesOrderHeader><List><SalesOrderLineItem><CurrencyCode>GBP</CurrencyCode><LineNumber>1</LineNumber><ProductCode>731788322427</ProductCode><Quantity>1</Quantity><UnitPrice>59.37</UnitPrice><VAT>11.88</VAT></SalesOrderLineItem></List></Request></Requests>
