<?xml version="1.0"?>
<Requests><Request><WebSalesOrder><SalesOrderNumber>FF-162466377</SalesOrderNumber><SalesOrderReference>5098767548494</SalesOrderReference><SalesOrderDate>2024-01-18T14:34:25+00:00</SalesOrderDate><CurrencyCode>GBP</CurrencyCode><CourierName>Customer Collect</CourierName><CourierService> </CourierService><Notes>Package_Type_5</Notes><GroupReference>Package_Type_5</GroupReference><OrderType>Web</OrderType></WebSalesOrder><DeliveryDetails><City>Milton Keynes</City><CountryCode>GB</CountryCode><EmailAddress>99744985@farfetch.com</EmailAddress><FirstName>FarFetch</FirstName><LastName>Seko Logistics</LastName><Line1>NING BO SHI HAI SHU QU NAN YUAN SHE QU YIN FENG LU </Line1><Line2>17 HAO BEI CHEN FU XIAO QU 7 CHUANG 18 DAN YUAN 2402 SHI</Line2><PhoneNumber/><PostcodeZip>MK10 0DF</PostcodeZip></DeliveryDetails><SalesOrderHeader><DCCode>DCCL01</DCCode></SalesOrderHeader><List><SalesOrderLineItem><CurrencyCode>GBP</CurrencyCode><LineNumber>1</LineNumber><ProductCode>724022971604</ProductCode><Quantity>1</Quantity><UnitPrice>96.59</UnitPrice><VAT>19.32</VAT></SalesOrderLineItem></List></Request></Requests>
