<?xml version="1.0"?>
<Requests><Request><WebSalesOrder><SalesOrderNumber>#GBP119807</SalesOrderNumber><SalesOrderReference>5212097249358</SalesOrderReference><SalesOrderDate>2024-05-03T19:48:25+01:00</SalesOrderDate><CurrencyCode>GBP</CurrencyCode><CourierName>Royal Mail</CourierName><CourierService>RMTRACKEDSTDNOSIG</CourierService><Notes>Package_Type_8</Notes><GroupReference>Package_Type_8</GroupReference><OrderType>Web</OrderType></WebSalesOrder><DeliveryDetails><City>London</City><CountryCode>GB</CountryCode><EmailAddress>rachael.wood@chintiandparker.com</EmailAddress><FirstName>rachael</FirstName><LastName>wood</LastName><Line1>15 Saint Quintin Avenue</Line1><PhoneNumber>07966 442304</PhoneNumber><PostcodeZip>W10 6NX</PostcodeZip></DeliveryDetails><SalesOrderHeader><DCCode>DCCL01</DCCode></SalesOrderHeader><List><SalesOrderLineItem><CurrencyCode>GBP</CurrencyCode><LineNumber>1</LineNumber><ProductCode>724022987155</ProductCode><Quantity>1</Quantity><UnitPrice>62.5</UnitPrice><VAT>12.5</VAT></SalesOrderLineItem><SalesOrderLineItem><CurrencyCode>GBP</CurrencyCode><LineNumber>2</LineNumber><ProductCode>724022987490</ProductCode><Quantity>1</Quantity><UnitPrice>70.83</UnitPrice><VAT>14.17</VAT></SalesOrderLineItem><SalesOrderLineItem><CurrencyCode>GBP</CurrencyCode><LineNumber>3</LineNumber><ProductCode>724022987674</ProductCode><Quantity>1</Quantity><UnitPrice>70.83</UnitPrice><VAT>14.17</VAT></SalesOrderLineItem><SalesOrderLineItem><CurrencyCode>GBP</CurrencyCode><LineNumber>4</LineNumber><ProductCode>724022901526</ProductCode><Quantity>1</Quantity><UnitPrice>162.5</UnitPrice><VAT>32.5</VAT></SalesOrderLineItem><SalesOrderLineItem><CurrencyCode>GBP</CurrencyCode><LineNumber>5</LineNumber><ProductCode>724022902721</ProductCode><Quantity>1</Quantity><UnitPrice>79.17</UnitPrice><VAT>15.83</VAT></SalesOrderLineItem><SalesOrderLineItem><CurrencyCode>GBP</CurrencyCode><LineNumber>6</LineNumber><ProductCode>724022900390</ProductCode><Quantity>1</Quantity><UnitPrice>62.5</UnitPrice><VAT>12.5</VAT></SalesOrderLineItem><SalesOrderLineItem><CurrencyCode>GBP</CurrencyCode><LineNumber>7</LineNumber><ProductCode>724022987261</ProductCode><Quantity>1</Quantity><UnitPrice>62.5</UnitPrice><VAT>12.5</VAT></SalesOrderLineItem><SalesOrderLineItem><CurrencyCode>GBP</CurrencyCode><LineNumber>8</LineNumber><ProductCode>724022900451</ProductCode><Quantity>1</Quantity><UnitPrice>62.5</UnitPrice><VAT>12.5</VAT></SalesOrderLineItem><SalesOrderLineItem><CurrencyCode>GBP</CurrencyCode><LineNumber>9</LineNumber><ProductCode>724022900512</ProductCode><Quantity>1</Quantity><UnitPrice>62.5</UnitPrice><VAT>12.5</VAT></SalesOrderLineItem><SalesOrderLineItem><CurrencyCode>GBP</CurrencyCode><LineNumber>10</LineNumber><ProductCode>724022987209</ProductCode><Quantity>1</Quantity><UnitPrice>62.5</UnitPrice><VAT>12.5</VAT></SalesOrderLineItem><SalesOrderLineItem><CurrencyCode>GBP</CurrencyCode><LineNumber>11</LineNumber><ProductCode>724022986608</ProductCode><Quantity>1</Quantity><UnitPrice>162.5</UnitPrice><VAT>32.5</VAT></SalesOrderLineItem><SalesOrderLineItem><CurrencyCode>GBP</CurrencyCode><LineNumber>12</LineNumber><ProductCode>724022986318</ProductCode><Quantity>1</Quantity><UnitPrice>162.5</UnitPrice><VAT>32.5</VAT></SalesOrderLineItem><SalesOrderLineItem><CurrencyCode>GBP</CurrencyCode><LineNumber>13</LineNumber><ProductCode>724022986783</ProductCode><Quantity>1</Quantity><UnitPrice>162.5</UnitPrice><VAT>32.5</VAT></SalesOrderLineItem><SalesOrderLineItem><CurrencyCode>GBP</CurrencyCode><LineNumber>14</LineNumber><ProductCode>724022986677</ProductCode><Quantity>1</Quantity><UnitPrice>208.33</UnitPrice><VAT>41.67</VAT></SalesOrderLineItem><SalesOrderLineItem><CurrencyCode>GBP</CurrencyCode><LineNumber>15</LineNumber><ProductCode>724022996751</ProductCode><Quantity>1</Quantity><UnitPrice>125</UnitPrice><VAT>25</VAT></SalesOrderLineItem><SalesOrderLineItem><CurrencyCode>GBP</CurrencyCode><LineNumber>16</LineNumber><ProductCode>724022996812</ProductCode><Quantity>1</Quantity><UnitPrice>104.17</UnitPrice><VAT>20.83</VAT></SalesOrderLineItem><SalesOrderLineItem><CurrencyCode>GBP</CurrencyCode><LineNumber>17</LineNumber><ProductCode>724022996805</ProductCode><Quantity>1</Quantity><UnitPrice>104.17</UnitPrice><VAT>20.83</VAT></SalesOrderLineItem><SalesOrderLineItem><CurrencyCode>GBP</CurrencyCode><LineNumber>18</LineNumber><ProductCode>724022985403</ProductCode><Quantity>1</Quantity><UnitPrice>162.5</UnitPrice><VAT>32.5</VAT></SalesOrderLineItem><SalesOrderLineItem><CurrencyCode>GBP</CurrencyCode><LineNumber>19</LineNumber><ProductCode>724022985502</ProductCode><Quantity>1</Quantity><UnitPrice>162.5</UnitPrice><VAT>32.5</VAT></SalesOrderLineItem></List></Request></Requests>
