<?xml version="1.0"?>
<Requests><Request><WebSalesOrder><SalesOrderNumber>#JL-156219</SalesOrderNumber><SalesOrderReference>5468697821269</SalesOrderReference><SalesOrderDate>2023-12-18T20:35:18+00:00</SalesOrderDate><CurrencyCode>GBP</CurrencyCode><CourierName>Royal Mail</CourierName><CourierService>RMTRACKEDSTDNOSIG</CourierService><Notes>Package_Type_9</Notes><GroupReference>Package_Type_9</GroupReference><OrderType>Web</OrderType></WebSalesOrder><DeliveryDetails><City>Tonbridge</City><CountryCode>GB</CountryCode><EmailAddress>andybolding@me.com</EmailAddress><FirstName>Andy</FirstName><LastName>Bolding</LastName><Line1>11 Well Close</Line1><Line2>Leigh</Line2><PhoneNumber>+447984950682</PhoneNumber><PostcodeZip>TN11 8RQ</PostcodeZip></DeliveryDetails><SalesOrderHeader><DCCode>DCCL01</DCCode></SalesOrderHeader><List><SalesOrderLineItem><CurrencyCode>GBP</CurrencyCode><LineNumber>1</LineNumber><ProductCode>744109868351</ProductCode><Quantity>1</Quantity><UnitPrice>54.17</UnitPrice><VAT>10.83</VAT></SalesOrderLineItem></List></Request></Requests>
