<?xml version="1.0"?>
<Requests><Request><WebSalesOrder><SalesOrderNumber>#GBP110944</SalesOrderNumber><SalesOrderReference>5048630280270</SalesOrderReference><SalesOrderDate>2023-11-30T09:17:15+00:00</SalesOrderDate><CurrencyCode>GBP</CurrencyCode><CourierName>DHL</CourierName><CourierService>DHLIREM</CourierService><Notes>Package_Type_1</Notes><GroupReference>Package_Type_1</GroupReference><OrderType>Web</OrderType></WebSalesOrder><DeliveryDetails><City>Santa Monica</City><CountryCode>US</CountryCode><EmailAddress>lailaaitken@gmail.com</EmailAddress><FirstName>Laila </FirstName><LastName>Aitken </LastName><Line1>323 San Vicente Blvd </Line1><Line2>Unit 1</Line2><PhoneNumber>(202) 4034740</PhoneNumber><PostcodeZip>90402</PostcodeZip></DeliveryDetails><SalesOrderHeader><DCCode>DCCL01</DCCode></SalesOrderHeader><List><SalesOrderLineItem><CurrencyCode>GBP</CurrencyCode><LineNumber>1</LineNumber><ProductCode>724022979396</ProductCode><Quantity>1</Quantity><UnitPrice>354.46</UnitPrice><VAT>0</VAT></SalesOrderLineItem></List></Request></Requests>
