<?xml version="1.0"?>
<Requests><Request><WebSalesOrder><SalesOrderNumber>#GBP111304</SalesOrderNumber><SalesOrderReference>5054603329614</SalesOrderReference><SalesOrderDate>2023-12-04T23:22:12+00:00</SalesOrderDate><CurrencyCode>GBP</CurrencyCode><CourierName>Royal Mail</CourierName><CourierService>RMTRACKEDSTDNOSIG</CourierService><Notes>Package_Type_3</Notes><GroupReference>Package_Type_3</GroupReference><OrderType>Web</OrderType></WebSalesOrder><DeliveryDetails><City>Loughton</City><CountryCode>GB</CountryCode><EmailAddress>zmbutler@btopenworld.com</EmailAddress><FirstName>Zoe</FirstName><LastName>Butler</LastName><Line1>16 Shelley Grove</Line1><Line2/><PhoneNumber>+44 2085020449</PhoneNumber><PostcodeZip>IG10 1BY</PostcodeZip></DeliveryDetails><SalesOrderHeader><DCCode>DCCL01</DCCode></SalesOrderHeader><List><SalesOrderLineItem><CurrencyCode>GBP</CurrencyCode><LineNumber>1</LineNumber><ProductCode>731788319847</ProductCode><Quantity>1</Quantity><UnitPrice>113.75</UnitPrice><VAT>22.75</VAT></SalesOrderLineItem><SalesOrderLineItem><CurrencyCode>GBP</CurrencyCode><LineNumber>2</LineNumber><ProductCode>731788320065</ProductCode><Quantity>1</Quantity><UnitPrice>113.75</UnitPrice><VAT>22.75</VAT></SalesOrderLineItem><SalesOrderLineItem><CurrencyCode>GBP</CurrencyCode><LineNumber>3</LineNumber><ProductCode>731788326265</ProductCode><Quantity>1</Quantity><UnitPrice>79.17</UnitPrice><VAT>15.83</VAT></SalesOrderLineItem></List></Request></Requests>
