<?xml version="1.0"?>
<Requests><Request><WebSalesOrder><SalesOrderNumber>4896998457422</SalesOrderNumber><SalesOrderReference>#GBP95005</SalesOrderReference><CourierName>DPD</CourierName><CourierService>PLNEXTDAY</CourierService><SalesOrderDate>2023-07-03T14:26:31+01:00</SalesOrderDate><CurrencyCode>GBP</CurrencyCode><GroupReference>WEB</GroupReference><Notes>Package_Type_3</Notes><OrderType>Web</OrderType></WebSalesOrder><DeliveryDetails><City>BROADSTONE</City><CountryCode>GB</CountryCode><EmailAddress>ambrosefashion@gmail.com</EmailAddress><FirstName>amber</FirstName><LastName>grant</LastName><Line1>81 Upton Way</Line1><PhoneNumber>+447966591019</PhoneNumber><PostcodeZip>BH18 9LX</PostcodeZip></DeliveryDetails><SalesOrderHeader><DCCode>DCCL01</DCCode></SalesOrderHeader><List><SalesOrderLineItem><CurrencyCode>GBP</CurrencyCode><LineNumber>1</LineNumber><ProductCode>731788300463</ProductCode><Quantity>1</Quantity><UnitPrice>79.17</UnitPrice><VAT>15.83</VAT></SalesOrderLineItem><SalesOrderLineItem><CurrencyCode>GBP</CurrencyCode><LineNumber>2</LineNumber><ProductCode>731788305864</ProductCode><Quantity>1</Quantity><UnitPrice>59.37</UnitPrice><VAT>11.88</VAT></SalesOrderLineItem><SalesOrderLineItem><CurrencyCode>GBP</CurrencyCode><LineNumber>3</LineNumber><ProductCode>731788307103</ProductCode><Quantity>1</Quantity><UnitPrice>47.5</UnitPrice><VAT>9.5</VAT></SalesOrderLineItem></List></Request></Requests>
