<?xml version="1.0"?>
<Requests><Request><WebSalesOrder><SalesOrderNumber>#GBP111244</SalesOrderNumber><SalesOrderReference>5053850746958</SalesOrderReference><SalesOrderDate>2023-12-04T12:38:31+00:00</SalesOrderDate><CurrencyCode>GBP</CurrencyCode><CourierName>Royal Mail</CourierName><CourierService>RMTRACKEDSTDNOSIG</CourierService><Notes>Package_Type_1</Notes><GroupReference>Package_Type_1</GroupReference><OrderType>Web</OrderType></WebSalesOrder><DeliveryDetails><City>London</City><CountryCode>GB</CountryCode><EmailAddress>sukeena@sukeenarao.com</EmailAddress><FirstName>Sukeena</FirstName><LastName>Rao</LastName><Line1>Westgrove </Line1><Line2>32 Kensington Park Road</Line2><Line3/><PhoneNumber>+447971677791</PhoneNumber><PostcodeZip>W11 3BU</PostcodeZip></DeliveryDetails><SalesOrderHeader><DCCode>DCCL01</DCCode></SalesOrderHeader><List><SalesOrderLineItem><CurrencyCode>GBP</CurrencyCode><LineNumber>1</LineNumber><ProductCode>724022973080</ProductCode><Quantity>1</Quantity><UnitPrice>113.75</UnitPrice><VAT>22.75</VAT></SalesOrderLineItem><SalesOrderLineItem><CurrencyCode>GBP</CurrencyCode><LineNumber>2</LineNumber><ProductCode>724022979211</ProductCode><Quantity>1</Quantity><UnitPrice>291.67</UnitPrice><VAT>58.33</VAT></SalesOrderLineItem><SalesOrderLineItem><CurrencyCode>GBP</CurrencyCode><LineNumber>3</LineNumber><ProductCode>769807731516</ProductCode><Quantity>1</Quantity><UnitPrice>375</UnitPrice><VAT>75</VAT></SalesOrderLineItem><SalesOrderLineItem><CurrencyCode>GBP</CurrencyCode><LineNumber>4</LineNumber><ProductCode>724022979273</ProductCode><Quantity>1</Quantity><UnitPrice>291.67</UnitPrice><VAT>58.33</VAT></SalesOrderLineItem><SalesOrderLineItem><CurrencyCode>GBP</CurrencyCode><LineNumber>5</LineNumber><ProductCode>724022980903</ProductCode><Quantity>1</Quantity><UnitPrice>375</UnitPrice><VAT>75</VAT></SalesOrderLineItem><SalesOrderLineItem><CurrencyCode>GBP</CurrencyCode><LineNumber>6</LineNumber><ProductCode>724022978207</ProductCode><Quantity>1</Quantity><UnitPrice>291.67</UnitPrice><VAT>58.33</VAT></SalesOrderLineItem><SalesOrderLineItem><CurrencyCode>GBP</CurrencyCode><LineNumber>7</LineNumber><ProductCode>724022979037</ProductCode><Quantity>1</Quantity><UnitPrice>291.67</UnitPrice><VAT>58.33</VAT></SalesOrderLineItem><SalesOrderLineItem><CurrencyCode>GBP</CurrencyCode><LineNumber>8</LineNumber><ProductCode>706502203863</ProductCode><Quantity>1</Quantity><UnitPrice>245.83</UnitPrice><VAT>49.17</VAT></SalesOrderLineItem><SalesOrderLineItem><CurrencyCode>GBP</CurrencyCode><LineNumber>9</LineNumber><ProductCode>724022979815</ProductCode><Quantity>1</Quantity><UnitPrice>245.83</UnitPrice><VAT>49.17</VAT></SalesOrderLineItem><SalesOrderLineItem><CurrencyCode>GBP</CurrencyCode><LineNumber>10</LineNumber><ProductCode>724022979570</ProductCode><Quantity>1</Quantity><UnitPrice>245.83</UnitPrice><VAT>49.17</VAT></SalesOrderLineItem></List></Request></Requests>
