<?xml version="1.0"?>
<Requests><Request><WebSalesOrder><SalesOrderNumber>#MPUSD-1823</SalesOrderNumber><SalesOrderReference>4181400748081</SalesOrderReference><SalesOrderDate>2023-10-10T13:47:05+01:00</SalesOrderDate><CurrencyCode>USD</CurrencyCode><CourierName>DHL</CourierName><CourierService>DHLIREM</CourierService><Notes>Package_Type_3</Notes><GroupReference>Package_Type_3</GroupReference><OrderType>Web</OrderType></WebSalesOrder><DeliveryDetails><City>&#x96F2;&#x6797;&#x7E23;</City><CountryCode>TW</CountryCode><EmailAddress>merch@ifchic.com</EmailAddress><FirstName>&#x6DD1;&#x5A77;</FirstName><LastName>&#x5433;</LastName><Line1>&#x6597;&#x516D;&#x5E02;&#x96F2;&#x79D1;&#x8DEF;&#x4E8C;&#x6BB5;109&#x865F;</Line1><Line2/><PhoneNumber>+886988088158</PhoneNumber><PostcodeZip>640</PostcodeZip></DeliveryDetails><SalesOrderHeader><DCCode>DCCL01</DCCode></SalesOrderHeader><List><SalesOrderLineItem><CurrencyCode>USD</CurrencyCode><LineNumber>1</LineNumber><ProductCode>731788313005</ProductCode><Quantity>1</Quantity><UnitPrice>125.00</UnitPrice><VAT>0</VAT></SalesOrderLineItem></List></Request></Requests>
